{
  "environment": "aws",
  "timestamp": "2025-11-30T12:22:09.948336Z",
  "experiments": {
    "A_deployment_speed": {
      "description": "Terraform deployment speed (destroy + apply)",
      "num_runs": 5,
      "operation": "destroy + apply",
      "times": {
        "count": 5,
        "min": 22.772,
        "max": 26.727,
        "mean": 24.813,
        "median": 24.853,
        "p90": 26.727,
        "p95": 26.727,
        "stdev": 1.924
      }
    },
    "B_e2e_timing": {
      "description": "End-to-end pipeline timing",
      "num_runs": 20,
      "rows_per_file": 1000,
      "failures": 2,
      "T_upload": {
        "count": 20,
        "min": 0.078,
        "max": 0.867,
        "mean": 0.144,
        "median": 0.085,
        "p90": 0.296,
        "p95": 0.867,
        "stdev": 0.181
      },
      "T_event_latency": {
        "count": 18,
        "min": 0.078,
        "max": 0.264,
        "mean": 0.096,
        "median": 0.086,
        "p90": 0.101,
        "p95": 0.264,
        "stdev": 0.042
      },
      "T_processing": {
        "count": 18,
        "min": 1.062,
        "max": 2.126,
        "mean": 1.59,
        "median": 1.596,
        "p90": 2.11,
        "p95": 2.126,
        "stdev": 0.532
      },
      "T_total_pipeline": {
        "count": 18,
        "min": 1.148,
        "max": 2.371,
        "mean": 1.686,
        "median": 1.683,
        "p90": 2.216,
        "p95": 2.371,
        "stdev": 0.545
      }
    },
    "D_failure_injection": {
      "description": "Error handling and failure scenarios",
      "test_cases": [
        {
          "test": "Empty File",
          "upload_success": true,
          "expected_status": "error",
          "actual_status": "error",
          "processing_time": 1.0802171230316162,
          "match": true,
          "error_message": "CSV file is empty or has no data rows"
        },
        {
          "test": "No Header",
          "upload_success": true,
          "expected_status": "error",
          "actual_status": "success",
          "processing_time": 1.0771739482879639,
          "match": true
        },
        {
          "test": "Malformed CSV",
          "upload_success": true,
          "expected_status": "error",
          "actual_status": "error",
          "processing_time": 2.10648512840271,
          "match": true,
          "error_message": "'list' object has no attribute 'strip'"
        },
        {
          "test": "Single Column",
          "upload_success": true,
          "expected_status": "success",
          "actual_status": "success",
          "processing_time": 2.1109540462493896,
          "match": true
        },
        {
          "test": "All Missing Values",
          "upload_success": true,
          "expected_status": "success",
          "actual_status": "success",
          "processing_time": 1.0699079036712646,
          "match": true
        },
        {
          "test": "Oversized Row",
          "upload_success": true,
          "expected_status": "success",
          "actual_status": "success",
          "processing_time": 2.095728874206543,
          "match": true
        }
      ],
      "total_tests": 6,
      "matches": 6
    },
    "F_file_size_scaling": {
      "description": "Performance scaling with file size",
      "results": [
        {
          "rows": 100,
          "file_size_kb": 6.4,
          "success": true,
          "upload_time": 0.074,
          "processing_time": 1.081,
          "total_time": 1.156,
          "throughput_rows_per_sec": 92.5
        },
        {
          "rows": 500,
          "file_size_kb": 32.1,
          "success": true,
          "upload_time": 0.081,
          "processing_time": 2.11,
          "total_time": 2.192,
          "throughput_rows_per_sec": 237.0
        },
        {
          "rows": 1000,
          "file_size_kb": 64.3,
          "success": true,
          "upload_time": 0.081,
          "processing_time": 1.071,
          "total_time": 1.154,
          "throughput_rows_per_sec": 933.7
        },
        {
          "rows": 5000,
          "file_size_kb": 325.6,
          "success": true,
          "upload_time": 0.124,
          "processing_time": 2.104,
          "total_time": 2.23,
          "throughput_rows_per_sec": 2376.4
        },
        {
          "rows": 10000,
          "file_size_kb": 652.3,
          "success": true,
          "upload_time": 0.135,
          "processing_time": 2.096,
          "total_time": 2.233,
          "throughput_rows_per_sec": 4771.1
        },
        {
          "rows": 20000,
          "file_size_kb": 1325.1,
          "success": true,
          "upload_time": 0.202,
          "processing_time": 2.103,
          "total_time": 2.306,
          "throughput_rows_per_sec": 9510.8
        }
      ]
    },
    "G_parallel_scaling": {
      "description": "Scaling behavior with parallel uploads",
      "results": [
        {
          "parallel_level": 1,
          "successful_uploads": 1,
          "successful_processing": 1,
          "upload_time": 0.08,
          "processing_time": 5.03,
          "upload_throughput": 12.57,
          "processing_throughput": 0.2
        },
        {
          "parallel_level": 5,
          "successful_uploads": 5,
          "successful_processing": 5,
          "upload_time": 0.249,
          "processing_time": 5.177,
          "upload_throughput": 20.09,
          "processing_throughput": 0.97
        },
        {
          "parallel_level": 10,
          "successful_uploads": 10,
          "successful_processing": 10,
          "upload_time": 0.333,
          "processing_time": 5.332,
          "upload_throughput": 30.07,
          "processing_throughput": 1.88
        },
        {
          "parallel_level": 20,
          "successful_uploads": 20,
          "successful_processing": 20,
          "upload_time": 0.76,
          "processing_time": 5.656,
          "upload_throughput": 26.31,
          "processing_throughput": 3.54
        },
        {
          "parallel_level": 50,
          "successful_uploads": 50,
          "successful_processing": 50,
          "upload_time": 1.771,
          "processing_time": 6.668,
          "upload_throughput": 28.23,
          "processing_throughput": 7.5
        },
        {
          "parallel_level": 100,
          "successful_uploads": 100,
          "successful_processing": 100,
          "upload_time": 1.545,
          "processing_time": 8.264,
          "upload_throughput": 64.72,
          "processing_throughput": 12.1
        }
      ]
    },
    "H_iam_fidelity": {
      "description": "IAM policy enforcement verification",
      "tests": [
        {
          "test": "Lambda read from uploads/",
          "expected": "allow",
          "actual": "allow",
          "matches": true
        },
        {
          "test": "Lambda write to processed/",
          "expected": "allow",
          "actual": "allow",
          "matches": true
        },
        {
          "test": "Lambda write to DynamoDB",
          "expected": "allow",
          "actual": "allow",
          "matches": true
        },
        {
          "test": "Lambda environment variables",
          "expected": "configured",
          "actual": "configured",
          "matches": true
        }
      ],
      "total_tests": 4,
      "matches": 4,
      "note": "Observational test only - does not modify IAM policies"
    }
  },
  "total_experiment_time": 704.55
}